ssfm-0.0.1.data/scripts/ssfm
ssfm_modules/__init__.py
ssfm_modules/core/__init__.py
ssfm_modules/core/wfm.py
ssfm_modules/core/wl.py
ssfm_modules/draw/__init__.py
ssfm_modules/draw/curs_dialog.py
ssfm_modules/draw/dialogs.py
ssfm_modules/draw/draw_mod.py
ssfm_modules/draw/space_tab.py
ssfm_modules/extensions/__init__.py
ssfm_modules/extensions/extension_handler.py
ssfm_modules/extensions/file_extension/__init__.py
ssfm_modules/extensions/file_extension/file_handler.py
ssfm_modules/extensions/git_extension/__init__.py
ssfm_modules/extensions/git_extension/git_handler.py
ssfm_modules/extensions/window_extension/__init__.py
ssfm_modules/extensions/window_extension/window_handler.py
ssfm-0.0.1.dist-info/LICENSE
ssfm-0.0.1.dist-info/METADATA
ssfm-0.0.1.dist-info/WHEEL
ssfm-0.0.1.dist-info/top_level.txt
ssfm-0.0.1.dist-info/RECORD
